<?xml version="1.0" encoding="utf-8" ?>
<dwsync>
<file name="100329_les_commandements_du_hipster_aspx_ss_image_10_jpg_902484264_north_320x.jpg" server="etudiant.univ-mlv.fr//home/6ima1a/bberthel/WWW/PHP/Projet/" local="130106958600000000" remote="130106958600000000" />
<file name="1326298192-324.jpg" server="etudiant.univ-mlv.fr//home/6ima1a/bberthel/WWW/PHP/Projet/" local="130106958600000000" remote="130106958600000000" />
<file name="1470e06d8ac2c1.jpg" server="etudiant.univ-mlv.fr//home/6ima1a/bberthel/WWW/PHP/Projet/" local="130106958600000000" remote="130106958600000000" />
<file name="20003719_0.jpg" server="etudiant.univ-mlv.fr//home/6ima1a/bberthel/WWW/PHP/Projet/" local="130095497400000000" remote="130095497400000000" />
<file name="9564f_Mac_Software_B001AMHWP8-1.jpg" server="etudiant.univ-mlv.fr//home/6ima1a/bberthel/WWW/PHP/Projet/" local="130095505800000000" remote="130095505800000000" />
<file name="acne.jpg" server="etudiant.univ-mlv.fr//home/6ima1a/bberthel/WWW/PHP/Projet/" local="130095489600000000" remote="130095489600000000" />
<file name="a-hipster-hotties-13_large.jpg" server="etudiant.univ-mlv.fr//home/6ima1a/bberthel/WWW/PHP/Projet/" local="130095503400000000" remote="130095503400000000" />
<file name="asos_backpack.jpg" server="etudiant.univ-mlv.fr//home/6ima1a/bberthel/WWW/PHP/Projet/" local="130095490200000000" remote="130095490200000000" />
<file name="asos_uo.jpg" server="etudiant.univ-mlv.fr//home/6ima1a/bberthel/WWW/PHP/Projet/" local="130095489000000000" remote="130095489000000000" />
<file name="asos_visiere_1.jpg" server="etudiant.univ-mlv.fr//home/6ima1a/bberthel/WWW/PHP/Projet/" local="130095490200000000" remote="130095490200000000" />
<file name="azoz.jpg" server="etudiant.univ-mlv.fr//home/6ima1a/bberthel/WWW/PHP/Projet/" local="130095489600000000" remote="130095489600000000" />
<file name="balenciaga_uo.jpg" server="etudiant.univ-mlv.fr//home/6ima1a/bberthel/WWW/PHP/Projet/" local="130095488400000000" remote="130095488400000000" />
<file name="banniÃšre-600x204.jpg" server="etudiant.univ-mlv.fr//home/6ima1a/bberthel/WWW/PHP/Projet/" local="130095495600000000" remote="130095495600000000" />
<file name="black-hipster-fashion-men-women.jpg" server="etudiant.univ-mlv.fr//home/6ima1a/bberthel/WWW/PHP/Projet/" local="130095490200000000" remote="130095490200000000" />
<file name="bonnet-barbe-hipster.jpg" server="etudiant.univ-mlv.fr//home/6ima1a/bberthel/WWW/PHP/Projet/" local="130095503400000000" remote="130095503400000000" />
<file name="bonnet-barbe.jpg" server="etudiant.univ-mlv.fr//home/6ima1a/bberthel/WWW/PHP/Projet/" local="130095503400000000" remote="130095503400000000" />
<file name="bonnetpois_asos_370805865.jpg" server="etudiant.univ-mlv.fr//home/6ima1a/bberthel/WWW/PHP/Projet/" local="130095503400000000" remote="130095503400000000" />
<file name="Bonnet-River-Island_reference.jpg" server="etudiant.univ-mlv.fr//home/6ima1a/bberthel/WWW/PHP/Projet/" local="130095503400000000" remote="130095503400000000" />
<file name="Carven_DG.jpg" server="etudiant.univ-mlv.fr//home/6ima1a/bberthel/WWW/PHP/Projet/" local="130095489600000000" remote="130095489600000000" />
<file name="casquette-1991-nasty-gal_a-la-mode-montreal1.jpg" server="etudiant.univ-mlv.fr//home/6ima1a/bberthel/WWW/PHP/Projet/" local="130095502800000000" remote="130095502800000000" />
<file name="cassette.jpg" server="etudiant.univ-mlv.fr//home/6ima1a/bberthel/WWW/PHP/Projet/" local="130095507600000000" remote="130095507600000000" />
<file name="cassette-tape.jpg" server="etudiant.univ-mlv.fr//home/6ima1a/bberthel/WWW/PHP/Projet/" local="130095507000000000" remote="130095507000000000" />
<file name="chanel.jpg" server="etudiant.univ-mlv.fr//home/6ima1a/bberthel/WWW/PHP/Projet/" local="130095490200000000" remote="130095490200000000" />
<file name="#chapeau3.jpg" server="etudiant.univ-mlv.fr//home/6ima1a/bberthel/WWW/PHP/Projet/" local="130106958600000000" remote="130106958600000000" />
<file name="chat-avec-casquette-4up.jpg" server="etudiant.univ-mlv.fr//home/6ima1a/bberthel/WWW/PHP/Projet/" local="130095502800000000" remote="130095502800000000" />
<file name="chaussettes.jpg" server="etudiant.univ-mlv.fr//home/6ima1a/bberthel/WWW/PHP/Projet/" local="130095489600000000" remote="130095489600000000" />
<file name="chaussettes_streetstyle.jpg" server="etudiant.univ-mlv.fr//home/6ima1a/bberthel/WWW/PHP/Projet/" local="130095489600000000" remote="130095489600000000" />
<file name="glasses-headband-hipster-smile-Favim.com-333203.jpg" server="etudiant.univ-mlv.fr//home/6ima1a/bberthel/WWW/PHP/Projet/" local="130095493800000000" remote="130095493800000000" />
<file name="hipster18.jpg" server="etudiant.univ-mlv.fr//home/6ima1a/bberthel/WWW/PHP/Projet/" local="130095493200000000" remote="130095493200000000" />
<file name="hipster1.jpeg" server="etudiant.univ-mlv.fr//home/6ima1a/bberthel/WWW/PHP/Projet/" local="130095492000000000" remote="130095492000000000" />
<file name="hipster1.jpg" server="etudiant.univ-mlv.fr//home/6ima1a/bberthel/WWW/PHP/Projet/" local="130095491400000000" remote="130095491400000000" />
<file name="hipster-604-564x261.jpg" server="etudiant.univ-mlv.fr//home/6ima1a/bberthel/WWW/PHP/Projet/" local="130095499800000000" remote="130095499800000000" />
<file name="hipster-contre-attaque-ba.jpg" server="etudiant.univ-mlv.fr//home/6ima1a/bberthel/WWW/PHP/Projet/" local="130095499800000000" remote="130095499800000000" />
<file name="hipster-dog.jpg" server="etudiant.univ-mlv.fr//home/6ima1a/bberthel/WWW/PHP/Projet/" local="130095501000000000" remote="130095501000000000" />
<file name="hipster-fashion-12.jpg" server="etudiant.univ-mlv.fr//home/6ima1a/bberthel/WWW/PHP/Projet/" local="130095491400000000" remote="130095491400000000" />
<file name="hipster_feathers.jpg" server="etudiant.univ-mlv.fr//home/6ima1a/bberthel/WWW/PHP/Projet/" local="130095487800000000" remote="130095487800000000" />
<file name="Hipster-Glasses-05.jpg" server="etudiant.univ-mlv.fr//home/6ima1a/bberthel/WWW/PHP/Projet/" local="130095496800000000" remote="130095496800000000" />
<file name="hipster headdress.jpg" server="etudiant.univ-mlv.fr//home/6ima1a/bberthel/WWW/PHP/Projet/" local="130095503400000000" remote="130095503400000000" />
<file name="hipster-hotties-16.jpg" server="etudiant.univ-mlv.fr//home/6ima1a/bberthel/WWW/PHP/Projet/" local="130095492000000000" remote="130095492000000000" />
<file name="hipster_jewelry.jpg" server="etudiant.univ-mlv.fr//home/6ima1a/bberthel/WWW/PHP/Projet/" local="130095487800000000" remote="130095487800000000" />
<file name="hipster.jpg" server="etudiant.univ-mlv.fr//home/6ima1a/bberthel/WWW/PHP/Projet/" local="130095506400000000" remote="130095506400000000" />
<file name="hipster-men-style-01.jpg" server="etudiant.univ-mlv.fr//home/6ima1a/bberthel/WWW/PHP/Projet/" local="130095490800000000" remote="130095490800000000" />
<file name="hipster_pantalon.jpg" server="etudiant.univ-mlv.fr//home/6ima1a/bberthel/WWW/PHP/Projet/" local="130095487800000000" remote="130095487800000000" />
<file name="hipster_shoes.jpg" server="etudiant.univ-mlv.fr//home/6ima1a/bberthel/WWW/PHP/Projet/" local="130095487800000000" remote="130095487800000000" />
<file name="hipsters.jpg" server="etudiant.univ-mlv.fr//home/6ima1a/bberthel/WWW/PHP/Projet/" local="130095488400000000" remote="130095488400000000" />
<file name="hipster-style-mustaches-ring-1v004.jpg" server="etudiant.univ-mlv.fr//home/6ima1a/bberthel/WWW/PHP/Projet/" local="130095496800000000" remote="130095496800000000" />
<file name="hipster_tattoo.jpg" server="etudiant.univ-mlv.fr//home/6ima1a/bberthel/WWW/PHP/Projet/" local="130095488400000000" remote="130095488400000000" />
<file name="hipster_tee.jpg" server="etudiant.univ-mlv.fr//home/6ima1a/bberthel/WWW/PHP/Projet/" local="130095487800000000" remote="130095487800000000" />
<file name="imac3.jpg" server="etudiant.univ-mlv.fr//home/6ima1a/bberthel/WWW/PHP/Projet/" local="130095505800000000" remote="130095505800000000" />
<file name="ipad-mini.jpg" server="etudiant.univ-mlv.fr//home/6ima1a/bberthel/WWW/PHP/Projet/" local="130095505800000000" remote="130095505800000000" />
<file name="la_coupe_hipster_vraiment_trop_hype_2449_north_320x.jpg" server="etudiant.univ-mlv.fr//home/6ima1a/bberthel/WWW/PHP/Projet/" local="130095501000000000" remote="130095501000000000" />
<file name="lunettes-hipster.jpg" server="etudiant.univ-mlv.fr//home/6ima1a/bberthel/WWW/PHP/Projet/" local="130095499200000000" remote="130095499200000000" />
<file name="MX_and_28mm_K.jpg" server="etudiant.univ-mlv.fr//home/6ima1a/bberthel/WWW/PHP/Projet/" local="130095496200000000" remote="130095496200000000" />
<file name="pendentif-hipster-lunettes-1v030.jpg" server="etudiant.univ-mlv.fr//home/6ima1a/bberthel/WWW/PHP/Projet/" local="130095496800000000" remote="130095496800000000" />
<file name="pendentif-hipster-moustaches-1v035.jpg" server="etudiant.univ-mlv.fr//home/6ima1a/bberthel/WWW/PHP/Projet/" local="130095496800000000" remote="130095496800000000" />
<file name="photos-argentiques.jpg" server="etudiant.univ-mlv.fr//home/6ima1a/bberthel/WWW/PHP/Projet/" local="130095495600000000" remote="130095495600000000" />
<file name="product_292964b.jpg" server="etudiant.univ-mlv.fr//home/6ima1a/bberthel/WWW/PHP/Projet/" local="130095496200000000" remote="130095496200000000" />
<file name="sandales_chaussettes.jpg" server="etudiant.univ-mlv.fr//home/6ima1a/bberthel/WWW/PHP/Projet/" local="130095489600000000" remote="130095489600000000" />
<file name="sandro_prada.jpg" server="etudiant.univ-mlv.fr//home/6ima1a/bberthel/WWW/PHP/Projet/" local="130095488400000000" remote="130095488400000000" />
<file name="Test-zone-numerique-fuji-x10-450-15.jpg" server="etudiant.univ-mlv.fr//home/6ima1a/bberthel/WWW/PHP/Projet/" local="130095495600000000" remote="130095495600000000" />
<file name="tumblr_lwtji5oIhi1r4xujn.jpg" server="etudiant.univ-mlv.fr//home/6ima1a/bberthel/WWW/PHP/Projet/" local="130095496200000000" remote="130095496200000000" />
<file name="tumblr_ly5j8oL4sq1qzgk72o1_500.jpg" server="etudiant.univ-mlv.fr//home/6ima1a/bberthel/WWW/PHP/Projet/" local="130095496800000000" remote="130095496800000000" />
<file name="tumblr_m48qz6kmTy1qfkglvo1_500.jpg" server="etudiant.univ-mlv.fr//home/6ima1a/bberthel/WWW/PHP/Projet/" local="130095502200000000" remote="130095502200000000" />
<file name="tumblr_m6vlgduwZJ1rqnes1o1_500.jpg" server="etudiant.univ-mlv.fr//home/6ima1a/bberthel/WWW/PHP/Projet/" local="130095508200000000" remote="130095508200000000" />
<file name="tumblr_mcrkck8IHJ1rvady5.jpg" server="etudiant.univ-mlv.fr//home/6ima1a/bberthel/WWW/PHP/Projet/" local="130095500400000000" remote="130095500400000000" />
<file name="uo.jpg" server="etudiant.univ-mlv.fr//home/6ima1a/bberthel/WWW/PHP/Projet/" local="130095489600000000" remote="130095489600000000" />
<file name="vinyl_hipster_by_kornkid4u-d3adkiy.jpg" server="etudiant.univ-mlv.fr//home/6ima1a/bberthel/WWW/PHP/Projet/" local="130095506400000000" remote="130095506400000000" />
<file name="Vinyl_record_LP_10inch.jpg" server="etudiant.univ-mlv.fr//home/6ima1a/bberthel/WWW/PHP/Projet/" local="130095505800000000" remote="130095505800000000" />
<file name="Wholesale-Lovely-hearts-heart-shaped-sunglasses-necessary-hipster-glasses-50pc-lot-free-shipping.jpg" server="etudiant.univ-mlv.fr//home/6ima1a/bberthel/WWW/PHP/Projet/" local="130095500400000000" remote="130095500400000000" />
<file name="902313_10200369527034337_1407871671_o.jpg" server="etudiant.univ-mlv.fr//home/6ima1a/bberthel/WWW/PHP/Projet/" local="130096462067139779" remote="130108264200000000" />
<file name="pull-bear-look-hipster-a-prix-casse.jpg" server="etudiant.univ-mlv.fr//home/6ima1a/bberthel/WWW/PHP/Projet/" local="130095614337431098" remote="130108264200000000" />
<file name="ws_Hipster_Glasses_1920x1200.jpg" server="etudiant.univ-mlv.fr//home/6ima1a/bberthel/WWW/PHP/Projet/" local="130095619820064687" remote="130108264200000000" />
</dwsync>